odoo/addons/sale_pricelist_item_advanced/README.rst
odoo/addons/sale_pricelist_item_advanced/__init__.py
odoo/addons/sale_pricelist_item_advanced/__manifest__.py
odoo/addons/sale_pricelist_item_advanced/i18n/es.po
odoo/addons/sale_pricelist_item_advanced/i18n/it.po
odoo/addons/sale_pricelist_item_advanced/i18n/sale_pricelist_item_advanced.pot
odoo/addons/sale_pricelist_item_advanced/readme/CONTRIBUTORS.rst
odoo/addons/sale_pricelist_item_advanced/readme/DESCRIPTION.rst
odoo/addons/sale_pricelist_item_advanced/readme/HISTORY.rst
odoo/addons/sale_pricelist_item_advanced/readme/USAGE.rst
odoo/addons/sale_pricelist_item_advanced/static/description/icon.png
odoo/addons/sale_pricelist_item_advanced/static/description/index.html
odoo/addons/sale_pricelist_item_advanced/views/product_pricelist_item.xml
odoo_addon_sale_pricelist_item_advanced-16.0.1.0.0.2.dist-info/METADATA
odoo_addon_sale_pricelist_item_advanced-16.0.1.0.0.2.dist-info/WHEEL
odoo_addon_sale_pricelist_item_advanced-16.0.1.0.0.2.dist-info/top_level.txt
odoo_addon_sale_pricelist_item_advanced-16.0.1.0.0.2.dist-info/RECORD
